arcade_pagerduty_api/__init__.py
arcade_pagerduty_api/moar/Pagerduty.json
arcade_pagerduty_api/moar/openapi.json
arcade_pagerduty_api/tools/__init__.py
arcade_pagerduty_api/tools/request_body_schemas.py
arcade_pagerduty_api/wrapper_tools/AddCacheVariableToServiceEvent.json
arcade_pagerduty_api/wrapper_tools/AddEscalationPolicyToTeam.json
arcade_pagerduty_api/wrapper_tools/AddIncidentNote.json
arcade_pagerduty_api/wrapper_tools/AddServiceFieldOption.json
arcade_pagerduty_api/wrapper_tools/AddUserToTeam.json
arcade_pagerduty_api/wrapper_tools/AssignTagsToPagerdutyEntity.json
arcade_pagerduty_api/wrapper_tools/AssociateAutomationActionWithService.json
arcade_pagerduty_api/wrapper_tools/AssociateAutomationActionWithTeam.json
arcade_pagerduty_api/wrapper_tools/AssociateRunnerWithTeam.json
arcade_pagerduty_api/wrapper_tools/AssociateServiceToIncidentWorkflowTrigger.json
arcade_pagerduty_api/wrapper_tools/CheckAbilityStatus.json
arcade_pagerduty_api/wrapper_tools/ClearBusinessServicePriorityThresholds.json
arcade_pagerduty_api/wrapper_tools/ConvertServiceEventRules.json
arcade_pagerduty_api/wrapper_tools/CreateAlertGroupingSetting.json
arcade_pagerduty_api/wrapper_tools/CreateAlertTemplate.json
arcade_pagerduty_api/wrapper_tools/CreateAutomationAction.json
arcade_pagerduty_api/wrapper_tools/CreateAutomationRunner.json
arcade_pagerduty_api/wrapper_tools/CreateBusinessService.json
arcade_pagerduty_api/wrapper_tools/CreateCacheVariableEventOrchestration.json
arcade_pagerduty_api/wrapper_tools/CreateCustomFieldOption.json
arcade_pagerduty_api/wrapper_tools/CreateEscalationPolicy.json
arcade_pagerduty_api/wrapper_tools/CreateEventIntegration.json
arcade_pagerduty_api/wrapper_tools/CreateEventRule.json
arcade_pagerduty_api/wrapper_tools/CreateGlobalEventOrchestration.json
arcade_pagerduty_api/wrapper_tools/CreateHandoffNotificationRule.json
arcade_pagerduty_api/wrapper_tools/CreateIncident.json
arcade_pagerduty_api/wrapper_tools/CreateIncidentResponderRequest.json
arcade_pagerduty_api-4.0.0.dist-info/METADATA
arcade_pagerduty_api-4.0.0.dist-info/WHEEL
arcade_pagerduty_api-4.0.0.dist-info/entry_points.txt
arcade_pagerduty_api-4.0.0.dist-info/licenses/LICENSE
arcade_pagerduty_api-4.0.0.dist-info/RECORD
